swarm_lib/__init__.py
swarm_lib/access_control.py
swarm_lib/agent.py
swarm_lib/broker_client.py
swarm_lib/consumer.py
swarm_lib/economy.py
swarm_lib/files.py
swarm_lib/provider.py
swarm_lib/service.py
swarm_lib/service_executor.py
swarm_lib-0.0.18.dist-info/METADATA
swarm_lib-0.0.18.dist-info/WHEEL
swarm_lib-0.0.18.dist-info/top_level.txt
swarm_lib-0.0.18.dist-info/RECORD
