Metadata-Version: 2.1
Name: swarm-lib
Version: 0.0.18
Summary: A Library for accessing the Swarm network written in Python
Home-page: UNKNOWN
Author: Geovane Fedrecheski
License: UNKNOWN
Platform: UNKNOWN
Requires-Dist: base58
Requires-Dist: ecdsa
Requires-Dist: flask
Requires-Dist: pycrypto
Requires-Dist: requests
Requires-Dist: wrap
